iga/__init__.py
iga/invariant_learning.py
pytorch_iga-0.0.3.dist-info/METADATA
pytorch_iga-0.0.3.dist-info/WHEEL
pytorch_iga-0.0.3.dist-info/top_level.txt
pytorch_iga-0.0.3.dist-info/RECORD
