Metadata-Version: 2.1
Name: pytorch-iga
Version: 0.0.3
Summary: A pytorch model training protocol for environment invariant deployment
Author-email: Calvin Boyce <calvinrboyce1@gmail.com>
License: MIT
Keywords: one,two
Classifier: Programming Language :: Python :: 3
Requires-Python: >=3.7
Requires-Dist: numpy
Requires-Dist: tqdm
Requires-Dist: torch
Requires-Dist: importlib-metadata ; python_version < "3.8"
Provides-Extra: dev
Requires-Dist: pytorch-iga[release,static-code-qa,test] ; extra == 'dev'
Provides-Extra: release
Requires-Dist: build ; extra == 'release'
Requires-Dist: twine ; extra == 'release'
Provides-Extra: static-code-qa
Requires-Dist: pre-commit ; extra == 'static-code-qa'
Provides-Extra: test
Requires-Dist: pytest ; extra == 'test'
Requires-Dist: pytest-cov ; extra == 'test'
